somap_py/__init__.py
somap_py/som_selector.py
somap_py/som_selector_gui.py
somap_py/somutils.py
somap_py-0.1.0.dist-info/METADATA
somap_py-0.1.0.dist-info/WHEEL
somap_py-0.1.0.dist-info/top_level.txt
somap_py-0.1.0.dist-info/RECORD
