Metadata-Version: 2.1
Name: somap-py
Version: 0.1.0
Summary: UNKNOWN
Home-page: https://bitbucket.org/dcdenu4/somap_py/src/master/
Author: Doug Denu
Author-email: ddenu@uvm.edu
License: Creative Commons Attribution-Noncommercial-Share Alike license
Platform: UNKNOWN
